configstack/__init__.py
configstack/_metadata.py
configstack/exceptions.py
configstack/layers.py
configstack/sources.py
configstack/structures.py
configstack/tests/__init__.py
configstack/tests/test_exceptions.py
configstack/tests/test_layers.py
configstack/tests/test_metadata.py
configstack/tests/test_sources.py
configstack/tests/test_structures.py
configstack-0.1.1.dist-info/DESCRIPTION.rst
configstack-0.1.1.dist-info/METADATA
configstack-0.1.1.dist-info/RECORD
configstack-0.1.1.dist-info/WHEEL
configstack-0.1.1.dist-info/metadata.json
configstack-0.1.1.dist-info/top_level.txt
